pyadaaah.py
pyadaaah-0.90.dist-info/LICENSE
pyadaaah-0.90.dist-info/METADATA
pyadaaah-0.90.dist-info/WHEEL
pyadaaah-0.90.dist-info/top_level.txt
pyadaaah-0.90.dist-info/RECORD
